ywpi_hub/__init__.py
ywpi_hub/__main__.py
ywpi_hub/agents_repository.py
ywpi_hub/app.py
ywpi_hub/channel.py
ywpi_hub/connection.py
ywpi_hub/events_router.py
ywpi_hub/hub_models.py
ywpi_hub/hub_pb2.py
ywpi_hub/hub_pb2.pyi
ywpi_hub/hub_pb2_grpc.py
ywpi_hub/logger.py
ywpi_hub/main.py
ywpi_hub/serialization.py
ywpi_hub/settings.py
ywpi_hub/streams_repository.py
ywpi_hub/tasks_respository.py
ywpi_hub/events/models.py
ywpi_hub/events/repository.py
ywpi_hub/tools/consumer.py
ywpi_hub-0.0.2.dist-info/METADATA
ywpi_hub-0.0.2.dist-info/WHEEL
ywpi_hub-0.0.2.dist-info/top_level.txt
ywpi_hub-0.0.2.dist-info/RECORD
