Metadata-Version: 2.4
Name: ywpi_hub
Version: 0.0.2
Requires-Dist: aiochannel>=1.3.0
Requires-Dist: bson>=0.5.10
Requires-Dist: grpcio==1.74.0
Requires-Dist: grpcio-tools==1.64.0
Requires-Dist: pydantic>=2.11.7
